MANIFEST.in
setup.py
django_fbapps.egg-info/PKG-INFO
django_fbapps.egg-info/SOURCES.txt
django_fbapps.egg-info/dependency_links.txt
django_fbapps.egg-info/top_level.txt
fbapps/__init__.py
fbapps/admin.py
fbapps/forms.py
fbapps/managers.py
fbapps/models.py
fbapps/urls.py
fbapps/utils.py
fbapps/views.py
fbapps/templates/fbapps/base.html
fbapps/tests/__init__.py
fbapps/tests/factories.py
fbapps/tests/flattab.py
fbapps/tests/generictab.py
fbapps/tests/mocks.py